open_binancian_futures/__init__.py
open_binancian_futures/__main__.py
open_binancian_futures/ai.py
open_binancian_futures/cli.py
open_binancian_futures/client.py
open_binancian_futures/constants.py
open_binancian_futures/exchange.py
open_binancian_futures/logging_config.py
open_binancian_futures/models.py
open_binancian_futures/py.typed
open_binancian_futures/runners.py
open_binancian_futures/strategy.py
open_binancian_futures/types.py
open_binancian_futures/utils.py
open_binancian_futures/webhook.py
open_binancian_futures-1.0.0b2.dist-info/licenses/LICENSE
open_binancian_futures-1.0.0b2.dist-info/METADATA
open_binancian_futures-1.0.0b2.dist-info/WHEEL
open_binancian_futures-1.0.0b2.dist-info/entry_points.txt
open_binancian_futures-1.0.0b2.dist-info/top_level.txt
open_binancian_futures-1.0.0b2.dist-info/RECORD
