Metadata-Version: 2.4
Name: open-binancian-futures
Version: 1.0.0b2
Summary: A robust framework for creating, backtesting, and deploying trading bots for Binance USDⓈ-M Futures
Author-email: HAN Sion <its.zionhan@gmail.com>
License: MIT
Project-URL: Homepage, https://github.com/zionhann/open-binancian-futures
Project-URL: Repository, https://github.com/zionhann/open-binancian-futures.git
Project-URL: Issues, https://github.com/zionhann/open-binancian-futures/issues
Keywords: binance,futures,trading,cryptocurrency,algorithmic-trading,backtesting,trading-bot
Classifier: Development Status :: 4 - Beta
Classifier: Intended Audience :: Financial and Insurance Industry
Classifier: License :: OSI Approved :: MIT License
Classifier: Programming Language :: Python :: 3
Classifier: Programming Language :: Python :: 3.12
Classifier: Programming Language :: Python :: 3.13
Classifier: Programming Language :: Python :: 3.14
Classifier: Typing :: Typed
Requires-Python: >=3.12
License-File: LICENSE
Requires-Dist: binance-sdk-derivatives-trading-usds-futures>=6.2.0
Requires-Dist: binance-common
Requires-Dist: numpy<2.4
Requires-Dist: pandas
Requires-Dist: pandas-ta
Requires-Dist: python-dotenv
Requires-Dist: pydantic-settings>=2.0.0
Requires-Dist: setuptools
Requires-Dist: TA-Lib
Requires-Dist: typer
Requires-Dist: openai
Requires-Dist: anthropic
Requires-Dist: toon-format>=0.9.0b1
Requires-Dist: tiktoken
Requires-Dist: slack-sdk
Provides-Extra: dev
Requires-Dist: pytest>=7.0; extra == "dev"
Requires-Dist: pytest-asyncio; extra == "dev"
Requires-Dist: pytest-cov; extra == "dev"
Requires-Dist: black; extra == "dev"
Requires-Dist: isort; extra == "dev"
Requires-Dist: mypy; extra == "dev"
Requires-Dist: ruff; extra == "dev"
Dynamic: license-file
